{
  "ticker": "CYTK",
  "success": true,
  "price": {
    "current": 62.51,
    "currency": "USD",
    "day_high": 64.97,
    "day_low": 62.28,
    "52_week_high": 70.98,
    "52_week_low": 29.31
  },
  "market_cap": {
    "value": 7642780672.0,
    "currency": "USD"
  },
  "shares_outstanding": 122264929.0,
  "volume": {
    "last": 2482911,
    "average_30d": 2228438
  },
  "valuation": {
    "pe_ratio": null,
    "forward_pe": -10.641286,
    "price_to_book": -14.666822
  },
  "company_info": {
    "name": "Cytokinetics, Incorporated",
    "sector": "Healthcare",
    "industry": "Biotechnology"
  },
  "data_quality": {
    "flags": [],
    "has_price": true,
    "has_market_cap": true,
    "has_volume": true
  },
  "provenance": {
    "source": "Yahoo Finance via yfinance",
    "timestamp": "2026-01-12T09:13:27.778456",
    "url": "https://finance.yahoo.com/quote/CYTK",
    "data_hash": "da790b23b70bcd10"
  }
}