{
  "ticker": "ESPR",
  "success": true,
  "price": {
    "current": 3.55,
    "currency": "USD",
    "day_high": 3.55,
    "day_low": 3.3948,
    "52_week_high": 4.18,
    "52_week_low": 0.69
  },
  "market_cap": {
    "value": 841595776.0,
    "currency": "USD"
  },
  "shares_outstanding": 237069239.0,
  "volume": {
    "last": 4679171,
    "average_30d": 5648060
  },
  "valuation": {
    "pe_ratio": null,
    "forward_pe": 57.789352,
    "price_to_book": -1.6158397
  },
  "company_info": {
    "name": "Esperion Therapeutics, Inc.",
    "sector": "Healthcare",
    "industry": "Drug Manufacturers - Specialty & Generic"
  },
  "balance_sheet": {
    "success": true,
    "period_date": "2025-09-30",
    "total_assets": 364020000.0,
    "total_liabilities": 815381000.0,
    "stockholders_equity": -451361000.0,
    "cash": 92447000.0,
    "marketable_securities": null,
    "total_liquidity": 92447000.0,
    "total_debt": 306795000.0,
    "long_term_debt": 248781000.0,
    "current_debt": 54863000.0,
    "error": null
  },
  "cash_flow": {
    "success": true,
    "period_date": "2025-09-30",
    "operating_cash_flow": -4286000.0,
    "free_cash_flow": -4286000.0,
    "investing_cash_flow": 0.0,
    "financing_cash_flow": 10672000.0,
    "error": null
  },
  "income_statement": {
    "success": true,
    "period_date": "2025-09-30",
    "operating_expense": 55979000.0,
    "research_and_development": 14131000.0,
    "interest_expense": 22051000.0,
    "net_income": -31333000.0,
    "revenue": 87309000.0,
    "gross_profit": 46020000.0,
    "ebitda": -9256000.0,
    "error": null
  },
  "data_quality": {
    "flags": [],
    "has_price": true,
    "has_market_cap": true,
    "has_volume": true,
    "has_balance_sheet": true,
    "has_cash_flow": true,
    "has_income_statement": true
  },
  "provenance": {
    "source": "Yahoo Finance via yfinance",
    "timestamp": "2026-01-29T16:46:01.380949",
    "url": "https://finance.yahoo.com/quote/ESPR",
    "data_hash": "5f822dedab2f7e8c"
  }
}