{
  "ticker": "NAUT",
  "success": true,
  "price": {
    "current": 1.94,
    "currency": "USD",
    "day_high": 2.15,
    "day_low": 1.91,
    "52_week_high": 2.54,
    "52_week_low": 0.62
  },
  "market_cap": {
    "value": 245031936.0,
    "currency": "USD"
  },
  "shares_outstanding": 126305122.0,
  "volume": {
    "last": 162448,
    "average_30d": 215636
  },
  "valuation": {
    "pe_ratio": null,
    "forward_pe": -2.6216216,
    "price_to_book": 1.4488425
  },
  "company_info": {
    "name": "Nautilus Biotechnology, Inc.",
    "sector": "Healthcare",
    "industry": "Biotechnology"
  },
  "balance_sheet": {
    "success": true,
    "period_date": "2025-09-30",
    "total_assets": 200915000.0,
    "total_liabilities": 31776000.0,
    "stockholders_equity": 169139000.0,
    "cash": 23875000.0,
    "marketable_securities": 107552000.0,
    "total_liquidity": 131427000.0,
    "total_debt": 27003000.0,
    "long_term_debt": 22794000.0,
    "current_debt": 4209000.0,
    "error": null
  },
  "cash_flow": {
    "success": true,
    "period_date": "2025-09-30",
    "operating_cash_flow": -11034000.0,
    "free_cash_flow": -11452000.0,
    "investing_cash_flow": 452000.0,
    "financing_cash_flow": 0.0,
    "error": null
  },
  "income_statement": {
    "success": true,
    "period_date": "2025-09-30",
    "operating_expense": 15472000.0,
    "research_and_development": 9605000.0,
    "interest_expense": null,
    "net_income": -13574000.0,
    "revenue": 0.0,
    "gross_profit": null,
    "ebitda": -13853000.0,
    "error": null
  },
  "data_quality": {
    "flags": [],
    "has_price": true,
    "has_market_cap": true,
    "has_volume": true,
    "has_balance_sheet": true,
    "has_cash_flow": true,
    "has_income_statement": true
  },
  "provenance": {
    "source": "Yahoo Finance via yfinance",
    "timestamp": "2026-01-29T16:49:40.971806",
    "url": "https://finance.yahoo.com/quote/NAUT",
    "data_hash": "9217842cc76a8394"
  }
}