{
  "ticker": "ZVRA",
  "success": true,
  "price": {
    "current": 8.49,
    "currency": "USD",
    "day_high": 8.86,
    "day_low": 8.47,
    "52_week_high": 13.16,
    "52_week_low": 6.19
  },
  "market_cap": {
    "value": 477966080.0,
    "currency": "USD"
  },
  "shares_outstanding": 56297535.0,
  "volume": {
    "last": 771964,
    "average_30d": 886709
  },
  "valuation": {
    "pe_ratio": 18.06383,
    "forward_pe": 13.693548,
    "price_to_book": 3.5837905
  },
  "company_info": {
    "name": "Zevra Therapeutics, Inc.",
    "sector": "Healthcare",
    "industry": "Biotechnology"
  },
  "data_quality": {
    "flags": [],
    "has_price": true,
    "has_market_cap": true,
    "has_volume": true
  },
  "provenance": {
    "source": "Yahoo Finance via yfinance",
    "timestamp": "2026-01-12T09:18:44.816567",
    "url": "https://finance.yahoo.com/quote/ZVRA",
    "data_hash": "7c7411f3a52aa5cb"
  }
}