<?xml version="1.0" encoding="UTF-8" standalone="yes"?>
<ns1:informationTable xmlns:ns1="http://www.sec.gov/edgar/document/thirteenf/informationtable">
	<ns1:infoTable>
		<ns1:nameOfIssuer>ABIVAX SA</ns1:nameOfIssuer>
		<ns1:titleOfClass>SPONSORED ADS</ns1:titleOfClass>
		<ns1:cusip>00370M103</ns1:cusip>
		<ns1:value>165555000</ns1:value>
		<ns1:shrsOrPrnAmt>
			<ns1:sshPrnamt>1950000</ns1:sshPrnamt>
			<ns1:sshPrnamtType>SH</ns1:sshPrnamtType>
		</ns1:shrsOrPrnAmt>
		<ns1:investmentDiscretion>DFND</ns1:investmentDiscretion>
		<ns1:otherManager>1</ns1:otherManager>
		<ns1:votingAuthority>
			<ns1:Sole>1950000</ns1:Sole>
			<ns1:Shared>0</ns1:Shared>
			<ns1:None>0</ns1:None>
		</ns1:votingAuthority>
	</ns1:infoTable>
	<ns1:infoTable>
		<ns1:nameOfIssuer>ALUMIS INC</ns1:nameOfIssuer>
		<ns1:titleOfClass>COM</ns1:titleOfClass>
		<ns1:cusip>022307102</ns1:cusip>
		<ns1:value>8568110</ns1:value>
		<ns1:shrsOrPrnAmt>
			<ns1:sshPrnamt>2147396</ns1:sshPrnamt>
			<ns1:sshPrnamtType>SH</ns1:sshPrnamtType>
		</ns1:shrsOrPrnAmt>
		<ns1:investmentDiscretion>DFND</ns1:investmentDiscretion>
		<ns1:otherManager>1</ns1:otherManager>
		<ns1:votingAuthority>
			<ns1:Sole>2147396</ns1:Sole>
			<ns1:Shared>0</ns1:Shared>
			<ns1:None>0</ns1:None>
		</ns1:votingAuthority>
	</ns1:infoTable>
	<ns1:infoTable>
		<ns1:nameOfIssuer>AMYLYX PHARMACEUTICALS INC</ns1:nameOfIssuer>
		<ns1:titleOfClass>COM</ns1:titleOfClass>
		<ns1:cusip>03237H101</ns1:cusip>
		<ns1:value>6795000</ns1:value>
		<ns1:shrsOrPrnAmt>
			<ns1:sshPrnamt>500000</ns1:sshPrnamt>
			<ns1:sshPrnamtType>SH</ns1:sshPrnamtType>
		</ns1:shrsOrPrnAmt>
		<ns1:investmentDiscretion>DFND</ns1:investmentDiscretion>
		<ns1:otherManager>1</ns1:otherManager>
		<ns1:votingAuthority>
			<ns1:Sole>500000</ns1:Sole>
			<ns1:Shared>0</ns1:Shared>
			<ns1:None>0</ns1:None>
		</ns1:votingAuthority>
	</ns1:infoTable>
	<ns1:infoTable>
		<ns1:nameOfIssuer>ARCELLX INC</ns1:nameOfIssuer>
		<ns1:titleOfClass>COMMON STOCK</ns1:titleOfClass>
		<ns1:cusip>03940C100</ns1:cusip>
		<ns1:value>63627500</ns1:value>
		<ns1:shrsOrPrnAmt>
			<ns1:sshPrnamt>775000</ns1:sshPrnamt>
			<ns1:sshPrnamtType>SH</ns1:sshPrnamtType>
		</ns1:shrsOrPrnAmt>
		<ns1:investmentDiscretion>DFND</ns1:investmentDiscretion>
		<ns1:otherManager>1</ns1:otherManager>
		<ns1:votingAuthority>
			<ns1:Sole>775000</ns1:Sole>
			<ns1:Shared>0</ns1:Shared>
			<ns1:None>0</ns1:None>
		</ns1:votingAuthority>
	</ns1:infoTable>
	<ns1:infoTable>
		<ns1:nameOfIssuer>ARCUTIS BIOTHERAPEUTICS INC</ns1:nameOfIssuer>
		<ns1:titleOfClass>COM</ns1:titleOfClass>
		<ns1:cusip>03969K108</ns1:cusip>
		<ns1:value>14608750</ns1:value>
		<ns1:shrsOrPrnAmt>
			<ns1:sshPrnamt>775000</ns1:sshPrnamt>
			<ns1:sshPrnamtType>SH</ns1:sshPrnamtType>
		</ns1:shrsOrPrnAmt>
		<ns1:investmentDiscretion>DFND</ns1:investmentDiscretion>
		<ns1:otherManager>1</ns1:otherManager>
		<ns1:votingAuthority>
			<ns1:Sole>775000</ns1:Sole>
			<ns1:Shared>0</ns1:Shared>
			<ns1:None>0</ns1:None>
		</ns1:votingAuthority>
	</ns1:infoTable>
	<ns1:infoTable>
		<ns1:nameOfIssuer>AVIDITY BIOSCIENCES INC</ns1:nameOfIssuer>
		<ns1:titleOfClass>COM</ns1:titleOfClass>
		<ns1:cusip>05370A108</ns1:cusip>
		<ns1:value>13071000</ns1:value>
		<ns1:shrsOrPrnAmt>
			<ns1:sshPrnamt>300000</ns1:sshPrnamt>
			<ns1:sshPrnamtType>SH</ns1:sshPrnamtType>
		</ns1:shrsOrPrnAmt>
		<ns1:investmentDiscretion>DFND</ns1:investmentDiscretion>
		<ns1:otherManager>1</ns1:otherManager>
		<ns1:votingAuthority>
			<ns1:Sole>300000</ns1:Sole>
			<ns1:Shared>0</ns1:Shared>
			<ns1:None>0</ns1:None>
		</ns1:votingAuthority>
	</ns1:infoTable>
	<ns1:infoTable>
		<ns1:nameOfIssuer>AXSOME THERAPEUTICS INC</ns1:nameOfIssuer>
		<ns1:titleOfClass>COM</ns1:titleOfClass>
		<ns1:cusip>05464T104</ns1:cusip>
		<ns1:value>12145000</ns1:value>
		<ns1:shrsOrPrnAmt>
			<ns1:sshPrnamt>100000</ns1:sshPrnamt>
			<ns1:sshPrnamtType>SH</ns1:sshPrnamtType>
		</ns1:shrsOrPrnAmt>
		<ns1:investmentDiscretion>DFND</ns1:investmentDiscretion>
		<ns1:otherManager>1</ns1:otherManager>
		<ns1:votingAuthority>
			<ns1:Sole>100000</ns1:Sole>
			<ns1:Shared>0</ns1:Shared>
			<ns1:None>0</ns1:None>
		</ns1:votingAuthority>
	</ns1:infoTable>
	<ns1:infoTable>
		<ns1:nameOfIssuer>BIOAGE LABS INC</ns1:nameOfIssuer>
		<ns1:titleOfClass>COM</ns1:titleOfClass>
		<ns1:cusip>09077V100</ns1:cusip>
		<ns1:value>12586757</ns1:value>
		<ns1:shrsOrPrnAmt>
			<ns1:sshPrnamt>2140605</ns1:sshPrnamt>
			<ns1:sshPrnamtType>SH</ns1:sshPrnamtType>
		</ns1:shrsOrPrnAmt>
		<ns1:investmentDiscretion>DFND</ns1:investmentDiscretion>
		<ns1:otherManager>1</ns1:otherManager>
		<ns1:votingAuthority>
			<ns1:Sole>2140605</ns1:Sole>
			<ns1:Shared>0</ns1:Shared>
			<ns1:None>0</ns1:None>
		</ns1:votingAuthority>
	</ns1:infoTable>
	<ns1:infoTable>
		<ns1:nameOfIssuer>BIOHAVEN LTD</ns1:nameOfIssuer>
		<ns1:titleOfClass>COM</ns1:titleOfClass>
		<ns1:cusip>G1110E107</ns1:cusip>
		<ns1:value>150100</ns1:value>
		<ns1:shrsOrPrnAmt>
			<ns1:sshPrnamt>10000</ns1:sshPrnamt>
			<ns1:sshPrnamtType>SH</ns1:sshPrnamtType>
		</ns1:shrsOrPrnAmt>
		<ns1:investmentDiscretion>DFND</ns1:investmentDiscretion>
		<ns1:otherManager>1</ns1:otherManager>
		<ns1:votingAuthority>
			<ns1:Sole>10000</ns1:Sole>
			<ns1:Shared>0</ns1:Shared>
			<ns1:None>0</ns1:None>
		</ns1:votingAuthority>
	</ns1:infoTable>
	<ns1:infoTable>
		<ns1:nameOfIssuer>BIOMEA FUSION INC</ns1:nameOfIssuer>
		<ns1:titleOfClass>COM</ns1:titleOfClass>
		<ns1:cusip>09077A106</ns1:cusip>
		<ns1:value>7213161</ns1:value>
		<ns1:shrsOrPrnAmt>
			<ns1:sshPrnamt>3570872</ns1:sshPrnamt>
			<ns1:sshPrnamtType>SH</ns1:sshPrnamtType>
		</ns1:shrsOrPrnAmt>
		<ns1:investmentDiscretion>DFND</ns1:investmentDiscretion>
		<ns1:otherManager>1</ns1:otherManager>
		<ns1:votingAuthority>
			<ns1:Sole>3570872</ns1:Sole>
			<ns1:Shared>0</ns1:Shared>
			<ns1:None>0</ns1:None>
		</ns1:votingAuthority>
	</ns1:infoTable>
	<ns1:infoTable>
		<ns1:nameOfIssuer>BRIDGEBIO ONCOLOGY THERAPEUT</ns1:nameOfIssuer>
		<ns1:titleOfClass>COM NEW</ns1:titleOfClass>
		<ns1:cusip>107924102</ns1:cusip>
		<ns1:value>207034119</ns1:value>
		<ns1:shrsOrPrnAmt>
			<ns1:sshPrnamt>17878594</ns1:sshPrnamt>
			<ns1:sshPrnamtType>SH</ns1:sshPrnamtType>
		</ns1:shrsOrPrnAmt>
		<ns1:investmentDiscretion>DFND</ns1:investmentDiscretion>
		<ns1:otherManager>1</ns1:otherManager>
		<ns1:votingAuthority>
			<ns1:Sole>17878594</ns1:Sole>
			<ns1:Shared>0</ns1:Shared>
			<ns1:None>0</ns1:None>
		</ns1:votingAuthority>
	</ns1:infoTable>
	<ns1:infoTable>
		<ns1:nameOfIssuer>BRIDGEBIO PHARMA INC</ns1:nameOfIssuer>
		<ns1:titleOfClass>COM</ns1:titleOfClass>
		<ns1:cusip>10806X102</ns1:cusip>
		<ns1:value>72716000</ns1:value>
		<ns1:shrsOrPrnAmt>
			<ns1:sshPrnamt>1400000</ns1:sshPrnamt>
			<ns1:sshPrnamtType>SH</ns1:sshPrnamtType>
		</ns1:shrsOrPrnAmt>
		<ns1:investmentDiscretion>DFND</ns1:investmentDiscretion>
		<ns1:otherManager>1</ns1:otherManager>
		<ns1:votingAuthority>
			<ns1:Sole>1400000</ns1:Sole>
			<ns1:Shared>0</ns1:Shared>
			<ns1:None>0</ns1:None>
		</ns1:votingAuthority>
	</ns1:infoTable>
	<ns1:infoTable>
		<ns1:nameOfIssuer>BRIGHT MINDS BIOSCIENCES INC</ns1:nameOfIssuer>
		<ns1:titleOfClass>COM NEW</ns1:titleOfClass>
		<ns1:cusip>10919W405</ns1:cusip>
		<ns1:value>64259018</ns1:value>
		<ns1:shrsOrPrnAmt>
			<ns1:sshPrnamt>1059331</ns1:sshPrnamt>
			<ns1:sshPrnamtType>SH</ns1:sshPrnamtType>
		</ns1:shrsOrPrnAmt>
		<ns1:investmentDiscretion>DFND</ns1:investmentDiscretion>
		<ns1:otherManager>1</ns1:otherManager>
		<ns1:votingAuthority>
			<ns1:Sole>1059331</ns1:Sole>
			<ns1:Shared>0</ns1:Shared>
			<ns1:None>0</ns1:None>
		</ns1:votingAuthority>
	</ns1:infoTable>
	<ns1:infoTable>
		<ns1:nameOfIssuer>CABALETTA BIO INC</ns1:nameOfIssuer>
		<ns1:titleOfClass>COM</ns1:titleOfClass>
		<ns1:cusip>12674W109</ns1:cusip>
		<ns1:value>11700000</ns1:value>
		<ns1:shrsOrPrnAmt>
			<ns1:sshPrnamt>5000000</ns1:sshPrnamt>
			<ns1:sshPrnamtType>SH</ns1:sshPrnamtType>
		</ns1:shrsOrPrnAmt>
		<ns1:investmentDiscretion>DFND</ns1:investmentDiscretion>
		<ns1:otherManager>1</ns1:otherManager>
		<ns1:votingAuthority>
			<ns1:Sole>5000000</ns1:Sole>
			<ns1:Shared>0</ns1:Shared>
			<ns1:None>0</ns1:None>
		</ns1:votingAuthority>
	</ns1:infoTable>
	<ns1:infoTable>
		<ns1:nameOfIssuer>CENTESSA PHARMACEUTICALS PLC</ns1:nameOfIssuer>
		<ns1:titleOfClass>SPONSORED ADS</ns1:titleOfClass>
		<ns1:cusip>152309100</ns1:cusip>
		<ns1:value>46681250</ns1:value>
		<ns1:shrsOrPrnAmt>
			<ns1:sshPrnamt>1925000</ns1:sshPrnamt>
			<ns1:sshPrnamtType>SH</ns1:sshPrnamtType>
		</ns1:shrsOrPrnAmt>
		<ns1:investmentDiscretion>DFND</ns1:investmentDiscretion>
		<ns1:otherManager>1</ns1:otherManager>
		<ns1:votingAuthority>
			<ns1:Sole>1925000</ns1:Sole>
			<ns1:Shared>0</ns1:Shared>
			<ns1:None>0</ns1:None>
		</ns1:votingAuthority>
	</ns1:infoTable>
	<ns1:infoTable>
		<ns1:nameOfIssuer>CG ONCOLOGY INC</ns1:nameOfIssuer>
		<ns1:titleOfClass>COM</ns1:titleOfClass>
		<ns1:cusip>156944100</ns1:cusip>
		<ns1:value>25175000</ns1:value>
		<ns1:shrsOrPrnAmt>
			<ns1:sshPrnamt>625000</ns1:sshPrnamt>
			<ns1:sshPrnamtType>SH</ns1:sshPrnamtType>
		</ns1:shrsOrPrnAmt>
		<ns1:investmentDiscretion>DFND</ns1:investmentDiscretion>
		<ns1:otherManager>1</ns1:otherManager>
		<ns1:votingAuthority>
			<ns1:Sole>625000</ns1:Sole>
			<ns1:Shared>0</ns1:Shared>
			<ns1:None>0</ns1:None>
		</ns1:votingAuthority>
	</ns1:infoTable>
	<ns1:infoTable>
		<ns1:nameOfIssuer>CORBUS PHARMACEUTICALS HLDGS</ns1:nameOfIssuer>
		<ns1:titleOfClass>COM NEW</ns1:titleOfClass>
		<ns1:cusip>21833P301</ns1:cusip>
		<ns1:value>30043750</ns1:value>
		<ns1:shrsOrPrnAmt>
			<ns1:sshPrnamt>2375000</ns1:sshPrnamt>
			<ns1:sshPrnamtType>SH</ns1:sshPrnamtType>
		</ns1:shrsOrPrnAmt>
		<ns1:investmentDiscretion>DFND</ns1:investmentDiscretion>
		<ns1:otherManager>1</ns1:otherManager>
		<ns1:votingAuthority>
			<ns1:Sole>2375000</ns1:Sole>
			<ns1:Shared>0</ns1:Shared>
			<ns1:None>0</ns1:None>
		</ns1:votingAuthority>
	</ns1:infoTable>
	<ns1:infoTable>
		<ns1:nameOfIssuer>CRINETICS PHARMACEUTICALS IN</ns1:nameOfIssuer>
		<ns1:titleOfClass>COM</ns1:titleOfClass>
		<ns1:cusip>22663K107</ns1:cusip>
		<ns1:value>16660000</ns1:value>
		<ns1:shrsOrPrnAmt>
			<ns1:sshPrnamt>400000</ns1:sshPrnamt>
			<ns1:sshPrnamtType>SH</ns1:sshPrnamtType>
		</ns1:shrsOrPrnAmt>
		<ns1:investmentDiscretion>DFND</ns1:investmentDiscretion>
		<ns1:otherManager>1</ns1:otherManager>
		<ns1:votingAuthority>
			<ns1:Sole>400000</ns1:Sole>
			<ns1:Shared>0</ns1:Shared>
			<ns1:None>0</ns1:None>
		</ns1:votingAuthority>
	</ns1:infoTable>
	<ns1:infoTable>
		<ns1:nameOfIssuer>EDGEWISE THERAPEUTICS INC</ns1:nameOfIssuer>
		<ns1:titleOfClass>COM</ns1:titleOfClass>
		<ns1:cusip>28036F105</ns1:cusip>
		<ns1:value>65042200</ns1:value>
		<ns1:shrsOrPrnAmt>
			<ns1:sshPrnamt>4010000</ns1:sshPrnamt>
			<ns1:sshPrnamtType>SH</ns1:sshPrnamtType>
		</ns1:shrsOrPrnAmt>
		<ns1:investmentDiscretion>DFND</ns1:investmentDiscretion>
		<ns1:otherManager>1</ns1:otherManager>
		<ns1:votingAuthority>
			<ns1:Sole>4010000</ns1:Sole>
			<ns1:Shared>0</ns1:Shared>
			<ns1:None>0</ns1:None>
		</ns1:votingAuthority>
	</ns1:infoTable>
	<ns1:infoTable>
		<ns1:nameOfIssuer>ENGENE HOLDINGS INC</ns1:nameOfIssuer>
		<ns1:titleOfClass>COM</ns1:titleOfClass>
		<ns1:cusip>29286M105</ns1:cusip>
		<ns1:value>15870154</ns1:value>
		<ns1:shrsOrPrnAmt>
			<ns1:sshPrnamt>2323595</ns1:sshPrnamt>
			<ns1:sshPrnamtType>SH</ns1:sshPrnamtType>
		</ns1:shrsOrPrnAmt>
		<ns1:investmentDiscretion>DFND</ns1:investmentDiscretion>
		<ns1:otherManager>1</ns1:otherManager>
		<ns1:votingAuthority>
			<ns1:Sole>2323595</ns1:Sole>
			<ns1:Shared>0</ns1:Shared>
			<ns1:None>0</ns1:None>
		</ns1:votingAuthority>
	</ns1:infoTable>
	<ns1:infoTable>
		<ns1:nameOfIssuer>ENLIVEN THERAPEUTICS INC</ns1:nameOfIssuer>
		<ns1:titleOfClass>COM</ns1:titleOfClass>
		<ns1:cusip>29337E102</ns1:cusip>
		<ns1:value>4094000</ns1:value>
		<ns1:shrsOrPrnAmt>
			<ns1:sshPrnamt>200000</ns1:sshPrnamt>
			<ns1:sshPrnamtType>SH</ns1:sshPrnamtType>
		</ns1:shrsOrPrnAmt>
		<ns1:investmentDiscretion>DFND</ns1:investmentDiscretion>
		<ns1:otherManager>1</ns1:otherManager>
		<ns1:votingAuthority>
			<ns1:Sole>200000</ns1:Sole>
			<ns1:Shared>0</ns1:Shared>
			<ns1:None>0</ns1:None>
		</ns1:votingAuthority>
	</ns1:infoTable>
	<ns1:infoTable>
		<ns1:nameOfIssuer>EYEPOINT PHARMACEUTICALS INC</ns1:nameOfIssuer>
		<ns1:titleOfClass>COM NEW</ns1:titleOfClass>
		<ns1:cusip>30233G209</ns1:cusip>
		<ns1:value>118548000</ns1:value>
		<ns1:shrsOrPrnAmt>
			<ns1:sshPrnamt>8325000</ns1:sshPrnamt>
			<ns1:sshPrnamtType>SH</ns1:sshPrnamtType>
		</ns1:shrsOrPrnAmt>
		<ns1:investmentDiscretion>DFND</ns1:investmentDiscretion>
		<ns1:otherManager>1</ns1:otherManager>
		<ns1:votingAuthority>
			<ns1:Sole>8325000</ns1:Sole>
			<ns1:Shared>0</ns1:Shared>
			<ns1:None>0</ns1:None>
		</ns1:votingAuthority>
	</ns1:infoTable>
	<ns1:infoTable>
		<ns1:nameOfIssuer>GH RESEARCH PLC</ns1:nameOfIssuer>
		<ns1:titleOfClass>ORDINARY SHARES</ns1:titleOfClass>
		<ns1:cusip>G3855L106</ns1:cusip>
		<ns1:value>27405078</ns1:value>
		<ns1:shrsOrPrnAmt>
			<ns1:sshPrnamt>1916439</ns1:sshPrnamt>
			<ns1:sshPrnamtType>SH</ns1:sshPrnamtType>
		</ns1:shrsOrPrnAmt>
		<ns1:investmentDiscretion>DFND</ns1:investmentDiscretion>
		<ns1:otherManager>1</ns1:otherManager>
		<ns1:votingAuthority>
			<ns1:Sole>1916439</ns1:Sole>
			<ns1:Shared>0</ns1:Shared>
			<ns1:None>0</ns1:None>
		</ns1:votingAuthority>
	</ns1:infoTable>
	<ns1:infoTable>
		<ns1:nameOfIssuer>INSMED INC</ns1:nameOfIssuer>
		<ns1:titleOfClass>COM PAR $.01</ns1:titleOfClass>
		<ns1:cusip>457669307</ns1:cusip>
		<ns1:value>61924300</ns1:value>
		<ns1:shrsOrPrnAmt>
			<ns1:sshPrnamt>430000</ns1:sshPrnamt>
			<ns1:sshPrnamtType>SH</ns1:sshPrnamtType>
		</ns1:shrsOrPrnAmt>
		<ns1:investmentDiscretion>DFND</ns1:investmentDiscretion>
		<ns1:otherManager>1</ns1:otherManager>
		<ns1:votingAuthority>
			<ns1:Sole>430000</ns1:Sole>
			<ns1:Shared>0</ns1:Shared>
			<ns1:None>0</ns1:None>
		</ns1:votingAuthority>
	</ns1:infoTable>
	<ns1:infoTable>
		<ns1:nameOfIssuer>JANUX THERAPEUTICS INC</ns1:nameOfIssuer>
		<ns1:titleOfClass>COM</ns1:titleOfClass>
		<ns1:cusip>47103J105</ns1:cusip>
		<ns1:value>20774000</ns1:value>
		<ns1:shrsOrPrnAmt>
			<ns1:sshPrnamt>850000</ns1:sshPrnamt>
			<ns1:sshPrnamtType>SH</ns1:sshPrnamtType>
		</ns1:shrsOrPrnAmt>
		<ns1:investmentDiscretion>DFND</ns1:investmentDiscretion>
		<ns1:otherManager>1</ns1:otherManager>
		<ns1:votingAuthority>
			<ns1:Sole>850000</ns1:Sole>
			<ns1:Shared>0</ns1:Shared>
			<ns1:None>0</ns1:None>
		</ns1:votingAuthority>
	</ns1:infoTable>
	<ns1:infoTable>
		<ns1:nameOfIssuer>KORRO BIO INC</ns1:nameOfIssuer>
		<ns1:titleOfClass>COM</ns1:titleOfClass>
		<ns1:cusip>500946108</ns1:cusip>
		<ns1:value>22268850</ns1:value>
		<ns1:shrsOrPrnAmt>
			<ns1:sshPrnamt>465000</ns1:sshPrnamt>
			<ns1:sshPrnamtType>SH</ns1:sshPrnamtType>
		</ns1:shrsOrPrnAmt>
		<ns1:investmentDiscretion>DFND</ns1:investmentDiscretion>
		<ns1:otherManager>1</ns1:otherManager>
		<ns1:votingAuthority>
			<ns1:Sole>465000</ns1:Sole>
			<ns1:Shared>0</ns1:Shared>
			<ns1:None>0</ns1:None>
		</ns1:votingAuthority>
	</ns1:infoTable>
	<ns1:infoTable>
		<ns1:nameOfIssuer>MBX BIOSCIENCES INC</ns1:nameOfIssuer>
		<ns1:titleOfClass>COM</ns1:titleOfClass>
		<ns1:cusip>55287L101</ns1:cusip>
		<ns1:value>21437500</ns1:value>
		<ns1:shrsOrPrnAmt>
			<ns1:sshPrnamt>1225000</ns1:sshPrnamt>
			<ns1:sshPrnamtType>SH</ns1:sshPrnamtType>
		</ns1:shrsOrPrnAmt>
		<ns1:investmentDiscretion>DFND</ns1:investmentDiscretion>
		<ns1:otherManager>1</ns1:otherManager>
		<ns1:votingAuthority>
			<ns1:Sole>1225000</ns1:Sole>
			<ns1:Shared>0</ns1:Shared>
			<ns1:None>0</ns1:None>
		</ns1:votingAuthority>
	</ns1:infoTable>
	<ns1:infoTable>
		<ns1:nameOfIssuer>METSERA INC</ns1:nameOfIssuer>
		<ns1:titleOfClass>COM</ns1:titleOfClass>
		<ns1:cusip>59267L107</ns1:cusip>
		<ns1:value>20932000</ns1:value>
		<ns1:shrsOrPrnAmt>
			<ns1:sshPrnamt>400000</ns1:sshPrnamt>
			<ns1:sshPrnamtType>SH</ns1:sshPrnamtType>
		</ns1:shrsOrPrnAmt>
		<ns1:investmentDiscretion>DFND</ns1:investmentDiscretion>
		<ns1:otherManager>1</ns1:otherManager>
		<ns1:votingAuthority>
			<ns1:Sole>400000</ns1:Sole>
			<ns1:Shared>0</ns1:Shared>
			<ns1:None>0</ns1:None>
		</ns1:votingAuthority>
	</ns1:infoTable>
	<ns1:infoTable>
		<ns1:nameOfIssuer>MOONLAKE IMMUNOTHERAPEUTICS</ns1:nameOfIssuer>
		<ns1:titleOfClass>CLASS A ORD</ns1:titleOfClass>
		<ns1:cusip>61559X104</ns1:cusip>
		<ns1:value>14298220</ns1:value>
		<ns1:shrsOrPrnAmt>
			<ns1:sshPrnamt>1994173</ns1:sshPrnamt>
			<ns1:sshPrnamtType>SH</ns1:sshPrnamtType>
		</ns1:shrsOrPrnAmt>
		<ns1:investmentDiscretion>DFND</ns1:investmentDiscretion>
		<ns1:otherManager>1</ns1:otherManager>
		<ns1:votingAuthority>
			<ns1:Sole>1994173</ns1:Sole>
			<ns1:Shared>0</ns1:Shared>
			<ns1:None>0</ns1:None>
		</ns1:votingAuthority>
	</ns1:infoTable>
	<ns1:infoTable>
		<ns1:nameOfIssuer>NEWAMSTERDAM PHARMA COMPANY</ns1:nameOfIssuer>
		<ns1:titleOfClass>ORDINARY SHARES</ns1:titleOfClass>
		<ns1:cusip>N62509109</ns1:cusip>
		<ns1:value>61857000</ns1:value>
		<ns1:shrsOrPrnAmt>
			<ns1:sshPrnamt>2175000</ns1:sshPrnamt>
			<ns1:sshPrnamtType>SH</ns1:sshPrnamtType>
		</ns1:shrsOrPrnAmt>
		<ns1:investmentDiscretion>DFND</ns1:investmentDiscretion>
		<ns1:otherManager>1</ns1:otherManager>
		<ns1:votingAuthority>
			<ns1:Sole>2175000</ns1:Sole>
			<ns1:Shared>0</ns1:Shared>
			<ns1:None>0</ns1:None>
		</ns1:votingAuthority>
	</ns1:infoTable>
	<ns1:infoTable>
		<ns1:nameOfIssuer>ORUKA THERAPEUTICS INC</ns1:nameOfIssuer>
		<ns1:titleOfClass>COM</ns1:titleOfClass>
		<ns1:cusip>687604108</ns1:cusip>
		<ns1:value>10256128</ns1:value>
		<ns1:shrsOrPrnAmt>
			<ns1:sshPrnamt>533340</ns1:sshPrnamt>
			<ns1:sshPrnamtType>SH</ns1:sshPrnamtType>
		</ns1:shrsOrPrnAmt>
		<ns1:investmentDiscretion>DFND</ns1:investmentDiscretion>
		<ns1:otherManager>1</ns1:otherManager>
		<ns1:votingAuthority>
			<ns1:Sole>533340</ns1:Sole>
			<ns1:Shared>0</ns1:Shared>
			<ns1:None>0</ns1:None>
		</ns1:votingAuthority>
	</ns1:infoTable>
	<ns1:infoTable>
		<ns1:nameOfIssuer>PHARVARIS N V</ns1:nameOfIssuer>
		<ns1:titleOfClass>COM</ns1:titleOfClass>
		<ns1:cusip>N69605108</ns1:cusip>
		<ns1:value>34011840</ns1:value>
		<ns1:shrsOrPrnAmt>
			<ns1:sshPrnamt>1363200</ns1:sshPrnamt>
			<ns1:sshPrnamtType>SH</ns1:sshPrnamtType>
		</ns1:shrsOrPrnAmt>
		<ns1:investmentDiscretion>DFND</ns1:investmentDiscretion>
		<ns1:otherManager>1</ns1:otherManager>
		<ns1:votingAuthority>
			<ns1:Sole>1363200</ns1:Sole>
			<ns1:Shared>0</ns1:Shared>
			<ns1:None>0</ns1:None>
		</ns1:votingAuthority>
	</ns1:infoTable>
	<ns1:infoTable>
		<ns1:nameOfIssuer>PRAXIS PRECISION MEDICINES I</ns1:nameOfIssuer>
		<ns1:titleOfClass>COM NEW</ns1:titleOfClass>
		<ns1:cusip>74006W207</ns1:cusip>
		<ns1:value>53000000</ns1:value>
		<ns1:shrsOrPrnAmt>
			<ns1:sshPrnamt>1000000</ns1:sshPrnamt>
			<ns1:sshPrnamtType>SH</ns1:sshPrnamtType>
		</ns1:shrsOrPrnAmt>
		<ns1:investmentDiscretion>DFND</ns1:investmentDiscretion>
		<ns1:otherManager>1</ns1:otherManager>
		<ns1:votingAuthority>
			<ns1:Sole>1000000</ns1:Sole>
			<ns1:Shared>0</ns1:Shared>
			<ns1:None>0</ns1:None>
		</ns1:votingAuthority>
	</ns1:infoTable>
	<ns1:infoTable>
		<ns1:nameOfIssuer>RAPPORT THERAPEUTICS INC</ns1:nameOfIssuer>
		<ns1:titleOfClass>COM</ns1:titleOfClass>
		<ns1:cusip>75383L102</ns1:cusip>
		<ns1:value>94817874</ns1:value>
		<ns1:shrsOrPrnAmt>
			<ns1:sshPrnamt>3192521</ns1:sshPrnamt>
			<ns1:sshPrnamtType>SH</ns1:sshPrnamtType>
		</ns1:shrsOrPrnAmt>
		<ns1:investmentDiscretion>DFND</ns1:investmentDiscretion>
		<ns1:otherManager>1</ns1:otherManager>
		<ns1:votingAuthority>
			<ns1:Sole>3192521</ns1:Sole>
			<ns1:Shared>0</ns1:Shared>
			<ns1:None>0</ns1:None>
		</ns1:votingAuthority>
	</ns1:infoTable>
	<ns1:infoTable>
		<ns1:nameOfIssuer>TARSUS PHARMACEUTICALS INC</ns1:nameOfIssuer>
		<ns1:titleOfClass>COM</ns1:titleOfClass>
		<ns1:cusip>87650L103</ns1:cusip>
		<ns1:value>17829000</ns1:value>
		<ns1:shrsOrPrnAmt>
			<ns1:sshPrnamt>300000</ns1:sshPrnamt>
			<ns1:sshPrnamtType>SH</ns1:sshPrnamtType>
		</ns1:shrsOrPrnAmt>
		<ns1:investmentDiscretion>DFND</ns1:investmentDiscretion>
		<ns1:otherManager>1</ns1:otherManager>
		<ns1:votingAuthority>
			<ns1:Sole>300000</ns1:Sole>
			<ns1:Shared>0</ns1:Shared>
			<ns1:None>0</ns1:None>
		</ns1:votingAuthority>
	</ns1:infoTable>
	<ns1:infoTable>
		<ns1:nameOfIssuer>VAXCYTE INC</ns1:nameOfIssuer>
		<ns1:titleOfClass>COM</ns1:titleOfClass>
		<ns1:cusip>92243G108</ns1:cusip>
		<ns1:value>6303500</ns1:value>
		<ns1:shrsOrPrnAmt>
			<ns1:sshPrnamt>175000</ns1:sshPrnamt>
			<ns1:sshPrnamtType>SH</ns1:sshPrnamtType>
		</ns1:shrsOrPrnAmt>
		<ns1:investmentDiscretion>DFND</ns1:investmentDiscretion>
		<ns1:otherManager>1</ns1:otherManager>
		<ns1:votingAuthority>
			<ns1:Sole>175000</ns1:Sole>
			<ns1:Shared>0</ns1:Shared>
			<ns1:None>0</ns1:None>
		</ns1:votingAuthority>
	</ns1:infoTable>
</ns1:informationTable>
